{"Bitterling": {"price": 900, "location": "1", "shadow size": "River", "time": [[0, 24]], "time_readable": "All day", "months": [5, 6, 7, 8, 9]}, "Pale chub": {"price": 200, "location": "1", "shadow size": "River", "time": [[9, 16]], "time_readable": "9am - 4pm", "months": [1, 2, 3, 4, 5, 6, 7, 8, 9, 10, 11, 12]}, "Crucian carp": {"price": 160, "location": "2", "shadow size": "River", "time": [[0, 24]], "time_readable": "All day", "months": [1, 2, 3, 4, 5, 6, 7, 8, 9, 10, 11, 12]}, "Dace": {"price": 240, "location": "3", "shadow size": "River", "time": [[16, 24], [0, 9]], "time_readable": "4pm - 9am", "months": [1, 2, 3, 4, 5, 6, 7, 8, 9, 10, 11, 12]}, "Carp": {"price": 300, "location": "4", "shadow size": "Pond", "time": [[0, 24]], "time_readable": "All day", "months": [1, 2, 3, 4, 5, 6, 7, 8, 9, 10, 11, 12]}, "Koi": {"price": 4000, "location": "4", "shadow size": "Pond", "time": [[16, 24], [0, 9]], "time_readable": "4pm - 9am", "months": [1, 2, 3, 4, 5, 6, 7, 8, 9, 10, 11, 12]}, "Goldfish": {"price": 1300, "location": "1", "shadow size": "Pond", "time": [[0, 24]], "time_readable": "All day", "months": [1, 2, 3, 4, 5, 6, 7, 8, 9, 10, 11, 12]}, "Pop-eyed goldfish": {"price": 1300, "location": "1", "shadow size": "Pond", "time": [[9, 16]], "time_readable": "9am - 4pm", "months": [1, 2, 3, 4, 5, 6, 7, 8, 9, 10, 11, 12]}, "Ranchu goldfish": {"price": 4500, "location": "2", "shadow size": "Pond", "time": [[9, 16]], "time_readable": "9am - 4pm", "months": [1, 2, 3, 4, 5, 6, 7, 8, 9, 10, 11, 12]}, "Killifish": {"price": 300, "location": "1", "shadow size": "Pond", "time": [[0, 24]], "time_readable": "All day", "months": [1, 2, 10, 11, 12]}, "Crawfish": {"price": 200, "location": "2", "shadow size": "Pond", "time": [[0, 24]], "time_readable": "All day", "months": [1, 2, 3, 10, 11, 12]}, "Soft-shelled turtle": {"price": 3750, "location": "4", "shadow size": "River", "time": [[16, 24], [0, 9]], "time_readable": "4pm - 9am", "months": [2, 3]}, "Snapping Turtle": {"price": 5000, "location": "5", "shadow size": "River", "time": [[21, 24], [0, 4]], "time_readable": "9pm - 4am", "months": [1, 2, 3, 4, 10, 11, 12]}, "Tadpole": {"price": 100, "location": "1", "shadow size": "Pond", "time": [[0, 24]], "time_readable": "All day", "months": [1, 9, 10, 11, 12]}, "Frog": {"price": 120, "location": "2", "shadow size": "Pond", "time": [[0, 24]], "time_readable": "All day", "months": [1, 2, 11, 12]}, "Freshwater goby": {"price": 400, "location": "2", "shadow size": "River", "time": [[16, 24], [0, 9]], "time_readable": "4pm - 9am", "months": [1, 2, 3, 4, 5, 6, 7, 8, 9, 10, 11, 12]}, "Loach": {"price": 400, "location": "2", "shadow size": "River", "time": [[0, 24]], "time_readable": "All day", "months": [9, 10, 11]}, "Catfish": {"price": 800, "location": "4", "shadow size": "Pond", "time": [[16, 24], [0, 9]], "time_readable": "4pm - 9am", "months": [1, 2, 3, 4, 11, 12]}, "Giant snakehead": {"price": 5500, "location": "5", "shadow size": "Pond", "time": [[9, 16]], "time_readable": "9am - 4pm", "months": [1, 2, 12]}, "Bluegill": {"price": 180, "location": "2", "shadow size": "River", "time": [[9, 16]], "time_readable": "9am - 4pm", "months": [1, 2, 3, 4, 5, 6, 7, 8, 9, 10, 11, 12]}, "Yellow perch": {"price": 300, "location": "3", "shadow size": "River", "time": [[0, 24]], "time_readable": "All day", "months": [4, 5, 6, 7, 8, 9]}, "Black bass": {"price": 400, "location": "4", "shadow size": "River", "time": [[0, 24]], "time_readable": "All day", "months": [1, 2, 3, 4, 5, 6, 7, 8, 9, 10, 11, 12]}, "Tilapia": {"price": 800, "location": "3", "shadow size": "River", "time": [[0, 24]], "time_readable": "All day", "months": [1, 2, 3, 4, 12]}, "Pike": {"price": 1800, "location": "5", "shadow size": "River", "time": [[0, 24]], "time_readable": "All day", "months": [3, 4, 5, 6]}, "Pond smelt": {"price": 500, "location": "2", "shadow size": "River", "time": [[0, 24]], "time_readable": "All day", "months": [6, 7, 8]}, "Sweetfish": {"price": 900, "location": "3", "shadow size": "River", "time": [[0, 24]], "time_readable": "All day", "months": [1, 2, 3]}, "Cherry salmon": {"price": 1000, "location": "3", "shadow size": "River (Clifftop) Pond", "time": [[16, 24], [0, 9]], "time_readable": "4pm - 9am", "months": [3, 4, 5, 9, 10, 11, 12]}, "Char": {"price": 3800, "location": "3", "shadow size": "River (Clifftop) Pond", "time": [[16, 24], [0, 9]], "time_readable": "4pm - 9am", "months": [3, 4, 5, 9, 10, 11, 12]}, "Golden trout": {"price": 15000, "location": "3", "shadow size": "River (Clifftop)", "time": [[16, 24], [0, 9]], "time_readable": "4pm - 9am", "months": [3, 4, 5, 9, 10, 11]}, "Stringfish": {"price": 15000, "location": "5", "shadow size": "River (Clifftop)", "time": [[16, 24], [0, 9]], "time_readable": "4pm - 9am", "months": [6, 7, 8, 9]}, "Salmon": {"price": 700, "location": "4", "shadow size": "River (Mouth)", "time": [[0, 24]], "time_readable": "All day", "months": [3]}, "King salmon": {"price": 1800, "location": "6", "shadow size": "River (Mouth)", "time": [[0, 24]], "time_readable": "All day", "months": [3]}, "Mitten crab": {"price": 2000, "location": "2", "shadow size": "River", "time": [[16, 24], [0, 9]], "time_readable": "4pm - 9am", "months": [3, 4, 5]}, "Guppy": {"price": 1300, "location": "1", "shadow size": "River", "time": [[9, 16]], "time_readable": "9am - 4pm", "months": [1, 2, 3, 4, 5, 10, 11, 12]}, "Nibble fish": {"price": 1500, "location": "1", "shadow size": "River", "time": [[9, 16]], "time_readable": "9am - 4pm", "months": [1, 2, 3, 11, 12]}, "Angelfish": {"price": 3000, "location": "2", "shadow size": "River", "time": [[16, 24], [0, 9]], "time_readable": "4pm - 9am", "months": [1, 2, 3, 4, 11, 12]}, "Betta": {"price": 2500, "location": "2", "shadow size": "River", "time": [[9, 16]], "time_readable": "9am - 4pm", "months": [1, 2, 3, 4, 11, 12]}, "Neon tetra": {"price": 500, "location": "1", "shadow size": "River", "time": [[9, 16]], "time_readable": "9am - 4pm", "months": [1, 2, 3, 4, 5, 10, 11, 12]}, "Rainbowfish": {"price": 800, "location": "1", "shadow size": "River", "time": [[9, 16]], "time_readable": "9am - 4pm", "months": [1, 2, 3, 4, 11, 12]}, "Piranha": {"price": 2500, "location": "2", "shadow size": "River", "time": [[9, 16], [21, 24], [0, 4]], "time_readable": "9am - 4pm & 9pm - 4am", "months": [1, 2, 3, 12]}, "Arowana": {"price": 10000, "location": "4", "shadow size": "River", "time": [[16, 24], [0, 9]], "time_readable": "4pm - 9am", "months": [1, 2, 3, 12]}, "Dorado": {"price": 15000, "location": "5", "shadow size": "River", "time": [[4, 21]], "time_readable": "4am - 9pm", "months": [1, 2, 3, 12]}, "Gar": {"price": 6000, "location": "6", "shadow size": "Pond", "time": [[16, 24], [0, 9]], "time_readable": "4pm - 9am", "months": [1, 2, 3, 12]}, "Arapaima": {"price": 10000, "location": "6", "shadow size": "River", "time": [[16, 24], [0, 9]], "time_readable": "4pm - 9am", "months": [1, 2, 3, 12]}, "Saddled bichir": {"price": 4000, "location": "4", "shadow size": "River", "time": [[21, 24], [0, 4]], "time_readable": "9pm - 4am", "months": [1, 2, 3, 12]}, "Sturgeon": {"price": 10000, "location": "6", "shadow size": "River (Mouth)", "time": [[0, 24]], "time_readable": "All day", "months": [3, 4, 5, 6, 7, 8, 9]}, "Sea butterfly": {"price": 1000, "location": "1", "shadow size": "Sea", "time": [[0, 24]], "time_readable": "All day", "months": [6, 7, 8, 9]}, "Sea horse": {"price": 1100, "location": "1", "shadow size": "Sea", "time": [[0, 24]], "time_readable": "All day", "months": [1, 2, 3, 4, 5, 10, 11, 12]}, "Clown fish": {"price": 650, "location": "1", "shadow size": "Sea", "time": [[0, 24]], "time_readable": "All day", "months": [1, 2, 3, 10, 11, 12]}, "Surgeonfish": {"price": 1000, "location": "2", "shadow size": "Sea", "time": [[0, 24]], "time_readable": "All day", "months": [1, 2, 3, 10, 11, 12]}, "Butterfly fish": {"price": 1000, "location": "2", "shadow size": "Sea", "time": [[0, 24]], "time_readable": "All day", "months": [1, 2, 3, 10, 11, 12]}, "Napoleonfish": {"price": 10000, "location": "6", "shadow size": "Sea", "time": [[4, 21]], "time_readable": "4am - 9pm", "months": [1, 2]}, "Zebra turkeyfish": {"price": 500, "location": "3", "shadow size": "Sea", "time": [[0, 24]], "time_readable": "All day", "months": [1, 2, 3, 4, 5, 10, 11, 12]}, "Blowfish": {"price": 5000, "location": "3", "shadow size": "Sea", "time": [[18, 24], [0, 4]], "time_readable": "6pm - 4am", "months": [5, 6, 7, 8]}, "Puffer fish": {"price": 250, "location": "3", "shadow size": "Sea", "time": [[0, 24]], "time_readable": "All day", "months": [1, 2, 3]}, "Anchovy": {"price": 200, "location": "2", "shadow size": "Sea", "time": [[4, 21]], "time_readable": "4am - 9pm", "months": [1, 2, 3, 4, 5, 6, 7, 8, 9, 10, 11, 12]}, "Horse mackerel": {"price": 150, "location": "2", "shadow size": "Sea", "time": [[0, 24]], "time_readable": "All day", "months": [1, 2, 3, 4, 5, 6, 7, 8, 9, 10, 11, 12]}, "Barred knifejaw": {"price": 5000, "location": "3", "shadow size": "Sea", "time": [[0, 24]], "time_readable": "All day", "months": [1, 2, 3, 4, 5, 9, 10, 11, 12]}, "Sea bass": {"price": 400, "location": "5", "shadow size": "Sea", "time": [[0, 24]], "time_readable": "All day", "months": [1, 2, 3, 4, 5, 6, 7, 8, 9, 10, 11, 12]}, "Red snapper": {"price": 3000, "location": "4", "shadow size": "Sea", "time": [[0, 24]], "time_readable": "All day", "months": [1, 2, 3, 4, 5, 6, 7, 8, 9, 10, 11, 12]}, "Dab": {"price": 300, "location": "3", "shadow size": "Sea", "time": [[0, 24]], "time_readable": "All day", "months": [4, 5, 6, 7, 8, 9, 10]}, "Olive flounder": {"price": 800, "location": "5", "shadow size": "Sea", "time": [[0, 24]], "time_readable": "All day", "months": [1, 2, 3, 4, 5, 6, 7, 8, 9, 10, 11, 12]}, "Squid": {"price": 500, "location": "3", "shadow size": "Sea", "time": [[0, 24]], "time_readable": "All day", "months": [1, 2, 6, 7, 8, 9, 10, 11, 12]}, "Moray eel": {"price": 2000, "location": "8", "shadow size": "Sea", "time": [[0, 24]], "time_readable": "All day", "months": [2, 3, 4]}, "Ribbon eel": {"price": 600, "location": "8", "shadow size": "Sea", "time": [[0, 24]], "time_readable": "All day", "months": [1, 2, 3, 4, 12]}, "Tuna": {"price": 7000, "location": "6", "shadow size": "Pier", "time": [[0, 24]], "time_readable": "All day", "months": [5, 6, 7, 8, 9, 10]}, "Blue marlin": {"price": 10000, "location": "6", "shadow size": "Pier", "time": [[0, 24]], "time_readable": "All day", "months": [1, 2, 3, 5, 6, 7, 8, 9, 10]}, "Giant trevally": {"price": 4500, "location": "5", "shadow size": "Pier", "time": [[0, 24]], "time_readable": "All day", "months": [1, 2, 3, 4, 11, 12]}, "Mahi-mahi": {"price": 6000, "location": "5", "shadow size": "Pier", "time": [[0, 24]], "time_readable": "All day", "months": [1, 2, 3, 4, 11, 12]}, "Ocean sunfish": {"price": 4000, "location": "7", "shadow size": "Sea", "time": [[4, 21]], "time_readable": "4am - 9pm", "months": [1, 2, 3]}, "Ray": {"price": 3000, "location": "5", "shadow size": "Sea", "time": [[4, 21]], "time_readable": "4am - 9pm", "months": [2, 3, 4, 5]}, "Saw shark": {"price": 12000, "location": "7", "shadow size": "Sea", "time": [[16, 24], [0, 9]], "time_readable": "4pm - 9am", "months": [1, 2, 3, 12]}, "Hammerhead shark": {"price": 8000, "location": "7", "shadow size": "Sea", "time": [[16, 24], [0, 9]], "time_readable": "4pm - 9am", "months": [1, 2, 3, 12]}, "Great white shark": {"price": 15000, "location": "7", "shadow size": "Sea", "time": [[16, 24], [0, 9]], "time_readable": "4pm - 9am", "months": [1, 2, 3, 12]}, "Whale shark": {"price": 13000, "location": "7", "shadow size": "Sea", "time": [[0, 24]], "time_readable": "All day", "months": [1, 2, 3, 12]}, "Suckerfish": {"price": 1500, "location": "9", "shadow size": "Sea", "time": [[0, 24]], "time_readable": "All day", "months": [1, 2, 3, 12]}, "Football fish": {"price": 2500, "location": "4", "shadow size": "Sea", "time": [[16, 24], [0, 9]], "time_readable": "4pm - 9am", "months": [5, 6, 7, 8, 9]}, "Oarfish": {"price": 9000, "location": "6", "shadow size": "Sea", "time": [[0, 24]], "time_readable": "All day", "months": [6, 7, 8, 9, 10, 11]}, "Barreleye": {"price": 15000, "location": "2", "shadow size": "Sea", "time": [[21, 24], [0, 4]], "time_readable": "9pm - 4am", "months": [1, 2, 3, 4, 5, 6, 7, 8, 9, 10, 11, 12]}, "Coelacanth": {"price": 15000, "location": "6", "shadow size": "Sea (Raining)", "time": [[0, 24]], "time_readable": "All day", "months": [1, 2, 3, 4, 5, 6, 7, 8, 9, 10, 11, 12]}}